CHANGES
LICENSE
MANIFEST.in
README.rst
ez_setup.py
requirements.txt
setup.py
test_requirements.txt
docs/Makefile
docs/conf.py
docs/index.rst
docs/make.bat
docs/getting-started/creating-new-project.rst
docs/getting-started/full_example.rst
docs/getting-started/index.rst
docs/getting-started/introduction.rst
docs/getting-started/mutable-dimensions.rst
docs/getting-started/project-settings.rst
docs/getting-started/running-scripts.rst
docs/getting-started/scheduling.rst
docs/getting-started/source-types.rst
docs/getting-started/table-constraints.rst
docs/getting-started/transform.rst
docs/getting-started/visualisation-tools.rst
docs/getting-started/writing-facts-and-dimensions.rst
pylytics/__init__.py
pylytics.egg-info/PKG-INFO
pylytics.egg-info/SOURCES.txt
pylytics.egg-info/dependency_links.txt
pylytics.egg-info/not-zip-safe
pylytics.egg-info/pbr.json
pylytics.egg-info/requires.txt
pylytics.egg-info/top_level.txt
pylytics/bin/pylytics-admin.py
pylytics/conf/__init__.py
pylytics/conf/mondrian_templates/__init__.py
pylytics/conf/mondrian_templates/mondrian_3/cube.jinja
pylytics/conf/project_template/__init__.py
pylytics/conf/project_template/client.cnf
pylytics/conf/project_template/manage.py
pylytics/conf/project_template/settings.py
pylytics/conf/project_template/dimension/__init__.py
pylytics/conf/project_template/dimension/store/__init__.py
pylytics/conf/project_template/dimension/store/extract.py
pylytics/conf/project_template/dimension/store/load.py
pylytics/conf/project_template/dimension/store/transform.py
pylytics/conf/project_template/fact/__init__.py
pylytics/conf/project_template/fact/sales/__init__.py
pylytics/conf/project_template/fact/sales/extract.py
pylytics/conf/project_template/fact/sales/load.py
pylytics/conf/project_template/fact/sales/transform.py
pylytics/conf/project_template/shared/__init__.py
pylytics/library/__init__.py
pylytics/library/column.py
pylytics/library/connection.py
pylytics/library/dimension.py
pylytics/library/exceptions.py
pylytics/library/fact.py
pylytics/library/log.py
pylytics/library/main.py
pylytics/library/schedule.py
pylytics/library/selector.py
pylytics/library/settings.py
pylytics/library/source.py
pylytics/library/system_settings.py
