Metadata-Version: 1.1
Name: pylytics
Version: 1.2.2
Summary: Build and manage a star schema.
Home-page: https://github.com/onefinestay/pylytics
Author: onefinestay
Author-email: engineering@onefinestay.com
License: UNKNOWN
Platform: UNKNOWN
Classifier: Development Status :: 4 - Beta
Classifier: Programming Language :: Python :: 2.7
Classifier: Intended Audience :: Developers
Classifier: Natural Language :: English
Classifier: Topic :: Software Development
Classifier: Topic :: Utilities
Classifier: Environment :: Console
